hefeng_weather_mcp/__init__.py
hefeng_weather_mcp/main.py
hefeng_weather_mcp-0.3.0.dist-info/licenses/license
hefeng_weather_mcp-0.3.0.dist-info/METADATA
hefeng_weather_mcp-0.3.0.dist-info/WHEEL
hefeng_weather_mcp-0.3.0.dist-info/entry_points.txt
hefeng_weather_mcp-0.3.0.dist-info/top_level.txt
hefeng_weather_mcp-0.3.0.dist-info/RECORD
