Metadata-Version: 2.4
Name: hefeng-weather-mcp
Version: 0.3.0
Summary: 和风天气 MCP 服务 - 基于 Model Context Protocol 的天气数据查询服务
Author-email: yeisme <yefun2004@gmail.com>
License: MIT
Project-URL: Homepage, https://github.com/yeisme/hefeng-weather-mcp
Project-URL: Repository, https://github.com/yeisme/hefeng-weather-mcp.git
Project-URL: Issues, https://github.com/yeisme/hefeng-weather-mcp/issues
Project-URL: Documentation, https://github.com/yeisme/hefeng-weather-mcp#readme
Keywords: weather,mcp,hefeng,qweather,climate
Classifier: Development Status :: 3 - Alpha
Classifier: Intended Audience :: Developers
Classifier: License :: OSI Approved :: MIT License
Classifier: Programming Language :: Python :: 3
Classifier: Programming Language :: Python :: 3.11
Classifier: Programming Language :: Python :: 3.12
Classifier: Programming Language :: Python :: 3.13
Classifier: Topic :: Scientific/Engineering :: Atmospheric Science
Classifier: Topic :: Internet :: WWW/HTTP :: Dynamic Content
Requires-Python: >=3.11
License-File: license
Requires-Dist: cryptography>=45.0.5
Requires-Dist: httpx>=0.28.1
Requires-Dist: mcp[cli]>=1.12.0
Requires-Dist: pyjwt>=2.10.1
Requires-Dist: python-dotenv>=1.1.1
Requires-Dist: typer>=0.16.0
Dynamic: license-file
